{
  "version": "7",
  "dialect": "postgresql",
  "entries": [
    {
      "idx": 0,
      "version": "7",
      "when": 1783045465187,
      "tag": "0000_init",
      "breakpoints": true
    },
    {
      "idx": 1,
      "version": "7",
      "when": 1783131028648,
      "tag": "0001_robust_mac_gargan",
      "breakpoints": true
    },
    {
      "idx": 2,
      "version": "7",
      "when": 1783143285183,
      "tag": "0002_complex_umar",
      "breakpoints": true
    },
    {
      "idx": 3,
      "version": "7",
      "when": 1783162171034,
      "tag": "0003_boring_carmella_unuscione",
      "breakpoints": true
    }
  ]
}